{"__type__":"cc.AnimationClip","_name":"skill101610201","_duration":1.0166666666666666,"speed":2,"wrapMode":2,"curveData":{"comps":{"cc.Sprite":{"spriteFrame":[{"frame":0,"value":{"__uuid__":"08TyUfP81HbZOGz/4WS81j"}},{"frame":0.16666666666666666,"value":{"__uuid__":"25CEFOfdhLU6kdXhGV0sGk"}},{"frame":0.3333333333333333,"value":{"__uuid__":"f0KNhqPFxM5Kb+gXD2Z3Lq"}},{"frame":0.5,"value":{"__uuid__":"26Nxk+jcFEMbXbgl3NtjOk"}},{"frame":0.6666666666666666,"value":{"__uuid__":"d7ssl1ybVFLpe35yqVVTmo"}},{"frame":0.8333333333333334,"value":{"__uuid__":"c27QBNZxRBwqUhw8uyawP5"}},{"frame":1,"value":{"__uuid__":"52ZZxE7blHvbKUwTZzcRV0"}}]}},"props":{"angle":[{"frame":0,"value":-45}]}}}